get_chromedriver.py
get_chromedriver_py-0.1.2.dist-info/LICENSE.rst
get_chromedriver_py-0.1.2.dist-info/METADATA
get_chromedriver_py-0.1.2.dist-info/WHEEL
get_chromedriver_py-0.1.2.dist-info/entry_points.txt
get_chromedriver_py-0.1.2.dist-info/top_level.txt
get_chromedriver_py-0.1.2.dist-info/RECORD
