Metadata-Version: 2.1
Name: get-chromedriver-py
Version: 0.1.2
Summary: Get chromedriver-py version most suitable for your system.
Home-page: https://github.com/barseghyanartur/get-chromedriver-py/
Author: Artur Barseghyan
Author-email: artur.barseghyan@gmail.com
License: MIT
Project-URL: Bug Tracker, https://github.com/barseghyanartur/get-chromedriver-py/issues
Project-URL: Documentation, https://get-chromedriver-py.readthedocs.io/
Project-URL: Source Code, https://github.com/barseghyanartur/get-chromedriver-py/
Project-URL: Changelog, https://get-chromedriver-py.readthedocs.io/en/latest/changelog.html
Keywords: get-chromedriver-py,chromedriver-py
Classifier: Programming Language :: Python :: 3.6
Classifier: Programming Language :: Python :: 3.7
Classifier: Programming Language :: Python :: 3.8
Classifier: Programming Language :: Python :: 3.9
Classifier: Programming Language :: Python :: 3.10
Classifier: Programming Language :: Python :: 3.11
Classifier: Environment :: Web Environment
Classifier: License :: OSI Approved :: MIT License
Classifier: Intended Audience :: Developers
Classifier: Operating System :: OS Independent
Classifier: Development Status :: 4 - Beta
Requires-Python: >=3.6
License-File: LICENSE.rst
